asm/__init__.py
autosnapmanager/__init__.py
autosnapmanager/asm.py
autosnapmanager/config.py
autosnapmanager/actions/__init__.py
autosnapmanager/actions/action_config.py
autosnapmanager/actions/clicks/__init__.py
autosnapmanager/actions/clicks/click.py
autosnapmanager/actions/clicks/click_config.py
autosnapmanager/actions/clicks/android/__init__.py
autosnapmanager/actions/clicks/android/adb_touch.py
autosnapmanager/actions/clicks/android/maatouch.py
autosnapmanager/actions/clicks/android/minitouch.py
autosnapmanager/actions/clicks/android/touch.py
autosnapmanager/actions/clicks/android/touch_config.py
autosnapmanager/actions/clicks/android/bin/maatouch
autosnapmanager/actions/clicks/android/bin/minitouch/libs/arm64-v8a/minitouch
autosnapmanager/actions/clicks/android/bin/minitouch/libs/arm64-v8a/minitouch-nopie
autosnapmanager/actions/clicks/android/bin/minitouch/libs/armeabi-v7a/minitouch
autosnapmanager/actions/clicks/android/bin/minitouch/libs/armeabi-v7a/minitouch-nopie
autosnapmanager/actions/clicks/android/bin/minitouch/libs/x86/minitouch
autosnapmanager/actions/clicks/android/bin/minitouch/libs/x86/minitouch-nopie
autosnapmanager/actions/clicks/android/bin/minitouch/libs/x86_64/minitouch
autosnapmanager/actions/clicks/android/bin/minitouch/libs/x86_64/minitouch-nopie
autosnapmanager/actions/clicks/windows/__init__.py
autosnapmanager/actions/clicks/windows/pyautogui_click.py
autosnapmanager/actions/clicks/windows/win32api_click.py
autosnapmanager/actions/clicks/windows/win32gui_click.py
autosnapmanager/managers/__init__.py
autosnapmanager/managers/android_manager.py
autosnapmanager/managers/manager.py
autosnapmanager/managers/manager_config.py
autosnapmanager/managers/windows_manager.py
autosnapmanager/matches/__init__.py
autosnapmanager/matches/match.py
autosnapmanager/matches/android/__init__.py
autosnapmanager/matches/android/opencv_match.py
autosnapmanager/matches/windows/__init__.py
autosnapmanager/matches/windows/opencv_match.py
autosnapmanager-0.1.1.dist-info/METADATA
autosnapmanager-0.1.1.dist-info/WHEEL
autosnapmanager-0.1.1.dist-info/top_level.txt
autosnapmanager-0.1.1.dist-info/RECORD
