Metadata-Version: 2.1
Name: autosnapmanager
Version: 0.1.1
Summary: Manager who integrates screenshot matching, click operations, and other operations.
Author-email: yxs <3556123651@qq.com>
License: MIT
Project-URL: Homepage, https://github.com/kibo1313/AutoSnapManager
Project-URL: Repository, https://github.com/kibo1313/AutoSnapManager
Keywords: screenshot,automation,manager
Classifier: Development Status :: 3 - Alpha
Classifier: Intended Audience :: Developers
Classifier: License :: OSI Approved :: MIT License
Classifier: Programming Language :: Python :: 3
Classifier: Programming Language :: Python :: 3.8
Classifier: Programming Language :: Python :: 3.9
Classifier: Programming Language :: Python :: 3.10
Requires-Python: >=3.8
Requires-Dist: loguru<1.0.0,>=0.7.3
Requires-Dist: PyGetWindow>=0.0.9
Requires-Dist: adbutils>=2.8.0
Requires-Dist: numpy>=1.24.4
Requires-Dist: opencv-python>=4.10.0.84
Requires-Dist: pywin32>=308
Requires-Dist: Pillow>=10.4.0
Requires-Dist: PyAutoGUI>=0.9.54
Requires-Dist: requests>=2.28.0
Provides-Extra: dev
Requires-Dist: pytest>=7.0.0; extra == "dev"
Requires-Dist: black>=22.0; extra == "dev"
Requires-Dist: flake8>=5.0.0; extra == "dev"
